<?xml version="1.0" encoding="UTF-8"?>
<kml xmlns="http://www.opengis.net/kml/2.2" xmlns:gx="http://www.google.com/kml/ext/2.2" xmlns:xsi="http://www.w3.org/2001/XMLSchema-instance" xsi:schemaLocation="http://www.opengis.net/kml/2.2 http://schemas.opengis.net/kml/2.2.0/ogckml22.xsd http://www.google.com/kml/ext/2.2 http://code.google.com/apis/kml/schema/kml22gx.xsd">
<Document id="TreeInventory2011">
    <Placemark id="ID_00872"><name>Fir</name><description><![CDATA[<p>1018 STITTSVILLE MAIN ST</p>]]></description>      <Point>        <coordinates> -75.93248685565754,45.2764923215054,0</coordinates>      </Point><Style><IconStyle><Icon><href>http://www.iconeasy.com/icon/thumbnails/Kids/Freestyle%20Icons/Tree%20Icon.jpg</href></Icon></IconStyle></Style>    </Placemark>    <Placemark id="ID_00874"><name>Fir</name><description><![CDATA[<p>1018 STITTSVILLE MAIN ST</p>]]></description>      <Point>        <coordinates> -75.93330946164777,45.27653214923022,0</coordinates>      </Point><Style><IconStyle><Icon><href>http://www.iconeasy.com/icon/thumbnails/Kids/Freestyle%20Icons/Tree%20Icon.jpg</href></Icon></IconStyle></Style>    </Placemark>    <Placemark id="ID_00875"><name>Fir</name><description><![CDATA[<p>1018 STITTSVILLE MAIN ST</p>]]></description>      <Point>        <coordinates> -75.93273564442148,45.2771545906965,0</coordinates>      </Point><Style><IconStyle><Icon><href>http://www.iconeasy.com/icon/thumbnails/Kids/Freestyle%20Icons/Tree%20Icon.jpg</href></Icon></IconStyle></Style>    </Placemark>    <Placemark id="ID_02648"><name>Fir</name><description><![CDATA[<p>563 FAIRVIEW AVE</p>]]></description>      <Point>        <coordinates> -75.67158174026356,45.45029392926176,0</coordinates>      </Point><Style><IconStyle><Icon><href>http://www.iconeasy.com/icon/thumbnails/Kids/Freestyle%20Icons/Tree%20Icon.jpg</href></Icon></IconStyle></Style>    </Placemark>    <Placemark id="ID_02649"><name>Fir</name><description><![CDATA[<p>570 FAIRVIEW AVE</p>]]></description>      <Point>        <coordinates> -75.67169455525742,45.45014662448695,0</coordinates>      </Point><Style><IconStyle><Icon><href>http://www.iconeasy.com/icon/thumbnails/Kids/Freestyle%20Icons/Tree%20Icon.jpg</href></Icon></IconStyle></Style>    </Placemark>    <Placemark id="ID_03826"><name>Fir</name><description><![CDATA[<p>1881 MONTEREAU AVE</p>]]></description>      <Point>        <coordinates> -75.54067997002339,45.44123096335626,0</coordinates>      </Point><Style><IconStyle><Icon><href>http://www.iconeasy.com/icon/thumbnails/Kids/Freestyle%20Icons/Tree%20Icon.jpg</href></Icon></IconStyle></Style>    </Placemark>    <Placemark id="ID_09048"><name>Fir</name><description><![CDATA[<p>1018 STITTSVILLE MAIN ST</p>]]></description>      <Point>        <coordinates> -75.93371125387584,45.27659606190199,0</coordinates>      </Point><Style><IconStyle><Icon><href>http://www.iconeasy.com/icon/thumbnails/Kids/Freestyle%20Icons/Tree%20Icon.jpg</href></Icon></IconStyle></Style>    </Placemark>    <Placemark id="ID_09053"><name>Fir</name><description><![CDATA[<p>1018 STITTSVILLE MAIN ST</p>]]></description>      <Point>        <coordinates> -75.93352020795949,45.27655444355274,0</coordinates>      </Point><Style><IconStyle><Icon><href>http://www.iconeasy.com/icon/thumbnails/Kids/Freestyle%20Icons/Tree%20Icon.jpg</href></Icon></IconStyle></Style>    </Placemark>    <Placemark id="ID_09152"><name>Fir</name><description><![CDATA[<p>1018 STITTSVILLE MAIN ST</p>]]></description>      <Point>        <coordinates> -75.93322965016333,45.27654739849836,0</coordinates>      </Point><Style><IconStyle><Icon><href>http://www.iconeasy.com/icon/thumbnails/Kids/Freestyle%20Icons/Tree%20Icon.jpg</href></Icon></IconStyle></Style>    </Placemark>    <Placemark id="ID_09153"><name>Fir</name><description><![CDATA[<p>1018 STITTSVILLE MAIN ST</p>]]></description>      <Point>        <coordinates> -75.93275728965845,45.27710797557716,0</coordinates>      </Point><Style><IconStyle><Icon><href>http://www.iconeasy.com/icon/thumbnails/Kids/Freestyle%20Icons/Tree%20Icon.jpg</href></Icon></IconStyle></Style>    </Placemark>    <Placemark id="ID_010083"><name>Fir</name><description><![CDATA[<p>11 REGAL CRES</p>]]></description>      <Point>        <coordinates> -75.83431220034764,45.20035255545638,0</coordinates>      </Point><Style><IconStyle><Icon><href>http://www.iconeasy.com/icon/thumbnails/Kids/Freestyle%20Icons/Tree%20Icon.jpg</href></Icon></IconStyle></Style>    </Placemark>    <Placemark id="ID_010566"><name>Fir</name><description><![CDATA[<p>454 CLOVERDALE RD</p>]]></description>      <Point>        <coordinates> -75.67429620689747,45.45217643250941,0</coordinates>      </Point><Style><IconStyle><Icon><href>http://www.iconeasy.com/icon/thumbnails/Kids/Freestyle%20Icons/Tree%20Icon.jpg</href></Icon></IconStyle></Style>    </Placemark>    <Placemark id="ID_010776"><name>Fir</name><description><![CDATA[<p>161 MARIPOSA AVE</p>]]></description>      <Point>        <coordinates> -75.68156645928889,45.44791940635389,0</coordinates>      </Point><Style><IconStyle><Icon><href>http://www.iconeasy.com/icon/thumbnails/Kids/Freestyle%20Icons/Tree%20Icon.jpg</href></Icon></IconStyle></Style>    </Placemark>    <Placemark id="ID_015588"><name>Fir</name><description><![CDATA[<p>1865 HUNTER'S RUN DR</p>]]></description>      <Point>        <coordinates> -75.52952206099813,45.45485039671478,0</coordinates>      </Point><Style><IconStyle><Icon><href>http://www.iconeasy.com/icon/thumbnails/Kids/Freestyle%20Icons/Tree%20Icon.jpg</href></Icon></IconStyle></Style>    </Placemark>    <Placemark id="ID_015598"><name>Fir</name><description><![CDATA[<p>1664 DES RAVINS PL</p>]]></description>      <Point>        <coordinates> -75.53810835032577,45.45253720421884,0</coordinates>      </Point><Style><IconStyle><Icon><href>http://www.iconeasy.com/icon/thumbnails/Kids/Freestyle%20Icons/Tree%20Icon.jpg</href></Icon></IconStyle></Style>    </Placemark>    <Placemark id="ID_017335"><name>Fir</name><description><![CDATA[<p>1018 STITTSVILLE MAIN ST</p>]]></description>      <Point>        <coordinates> -75.93344425151415,45.27656923245571,0</coordinates>      </Point><Style><IconStyle><Icon><href>http://www.iconeasy.com/icon/thumbnails/Kids/Freestyle%20Icons/Tree%20Icon.jpg</href></Icon></IconStyle></Style>    </Placemark>    <Placemark id="ID_017407"><name>Fir</name><description><![CDATA[<p>1018 STITTSVILLE MAIN ST</p>]]></description>      <Point>        <coordinates> -75.93355419136395,45.2765749466725,0</coordinates>      </Point><Style><IconStyle><Icon><href>http://www.iconeasy.com/icon/thumbnails/Kids/Freestyle%20Icons/Tree%20Icon.jpg</href></Icon></IconStyle></Style>    </Placemark>    <Placemark id="ID_017408"><name>Fir</name><description><![CDATA[<p>1018 STITTSVILLE MAIN ST</p>]]></description>      <Point>        <coordinates> -75.93275828815965,45.27713657869496,0</coordinates>      </Point><Style><IconStyle><Icon><href>http://www.iconeasy.com/icon/thumbnails/Kids/Freestyle%20Icons/Tree%20Icon.jpg</href></Icon></IconStyle></Style>    </Placemark>    <Placemark id="ID_019086"><name>Fir</name><description><![CDATA[<p>563 FAIRVIEW AVE</p>]]></description>      <Point>        <coordinates> -75.67185865383627,45.45022529801609,0</coordinates>      </Point><Style><IconStyle><Icon><href>http://www.iconeasy.com/icon/thumbnails/Kids/Freestyle%20Icons/Tree%20Icon.jpg</href></Icon></IconStyle></Style>    </Placemark>    <Placemark id="ID_020247"><name>Fir</name><description><![CDATA[<p>6027 BELCASTLE CRT</p>]]></description>      <Point>        <coordinates> -75.54761718061273,45.45375674366669,0</coordinates>      </Point><Style><IconStyle><Icon><href>http://www.iconeasy.com/icon/thumbnails/Kids/Freestyle%20Icons/Tree%20Icon.jpg</href></Icon></IconStyle></Style>    </Placemark>    <Placemark id="ID_020256"><name>Fir</name><description><![CDATA[<p>1600 FOREST RIDGE PL</p>]]></description>      <Point>        <coordinates> -75.54625534763157,45.45253461833853,0</coordinates>      </Point><Style><IconStyle><Icon><href>http://www.iconeasy.com/icon/thumbnails/Kids/Freestyle%20Icons/Tree%20Icon.jpg</href></Icon></IconStyle></Style>    </Placemark>    <Placemark id="ID_020316"><name>Fir</name><description><![CDATA[<p>1881 MONTEREAU AVE</p>]]></description>      <Point>        <coordinates> -75.5407997306061,45.44118749117742,0</coordinates>      </Point><Style><IconStyle><Icon><href>http://www.iconeasy.com/icon/thumbnails/Kids/Freestyle%20Icons/Tree%20Icon.jpg</href></Icon></IconStyle></Style>    </Placemark>    <Placemark id="ID_020724"><name>Fir</name><description><![CDATA[<p>125 LANSDOWNE RD</p>]]></description>      <Point>        <coordinates> -75.66893172596892,45.44820093847579,0</coordinates>      </Point><Style><IconStyle><Icon><href>http://www.iconeasy.com/icon/thumbnails/Kids/Freestyle%20Icons/Tree%20Icon.jpg</href></Icon></IconStyle></Style>    </Placemark>    <Placemark id="ID_021567"><name>Fir</name><description><![CDATA[<p>1018 STITTSVILLE MAIN ST</p>]]></description>      <Point>        <coordinates> -75.93320098651539,45.27652270754798,0</coordinates>      </Point><Style><IconStyle><Icon><href>http://www.iconeasy.com/icon/thumbnails/Kids/Freestyle%20Icons/Tree%20Icon.jpg</href></Icon></IconStyle></Style>    </Placemark>    <Placemark id="ID_024282"><name>Fir</name><description><![CDATA[<p>1607 FOREST RIDGE PL</p>]]></description>      <Point>        <coordinates> -75.54643323519757,45.45171068929285,0</coordinates>      </Point><Style><IconStyle><Icon><href>http://www.iconeasy.com/icon/thumbnails/Kids/Freestyle%20Icons/Tree%20Icon.jpg</href></Icon></IconStyle></Style>    </Placemark>    <Placemark id="ID_024667"><name>Fir</name><description><![CDATA[<p>26 PORTADOWN CRES</p>]]></description>      <Point>        <coordinates> -75.9438151139415,45.35032200478275,0</coordinates>      </Point><Style><IconStyle><Icon><href>http://www.iconeasy.com/icon/thumbnails/Kids/Freestyle%20Icons/Tree%20Icon.jpg</href></Icon></IconStyle></Style>    </Placemark>    <Placemark id="ID_024763"><name>Fir</name><description><![CDATA[<p>175 LANSDOWNE RD</p>]]></description>      <Point>        <coordinates> -75.6693705153868,45.44833003235208,0</coordinates>      </Point><Style><IconStyle><Icon><href>http://www.iconeasy.com/icon/thumbnails/Kids/Freestyle%20Icons/Tree%20Icon.jpg</href></Icon></IconStyle></Style>    </Placemark>    <Placemark id="ID_025587"><name>Fir</name><description><![CDATA[<p>1018 STITTSVILLE MAIN ST</p>]]></description>      <Point>        <coordinates> -75.93358644320648,45.27655478465189,0</coordinates>      </Point><Style><IconStyle><Icon><href>http://www.iconeasy.com/icon/thumbnails/Kids/Freestyle%20Icons/Tree%20Icon.jpg</href></Icon></IconStyle></Style>    </Placemark>    <Placemark id="ID_029271"><name>Fir</name><description><![CDATA[<p>5 TAUNTON PL</p>]]></description>      <Point>        <coordinates> -75.61350038271841,45.44937431916525,0</coordinates>      </Point><Style><IconStyle><Icon><href>http://www.iconeasy.com/icon/thumbnails/Kids/Freestyle%20Icons/Tree%20Icon.jpg</href></Icon></IconStyle></Style>    </Placemark>    <Placemark id="ID_029549"><name>Fir</name><description><![CDATA[<p>1018 STITTSVILLE MAIN ST</p>]]></description>      <Point>        <coordinates> -75.93340825361869,45.27654624194211,0</coordinates>      </Point><Style><IconStyle><Icon><href>http://www.iconeasy.com/icon/thumbnails/Kids/Freestyle%20Icons/Tree%20Icon.jpg</href></Icon></IconStyle></Style>    </Placemark>    <Placemark id="ID_031701"><name>Fir</name><description><![CDATA[<p>11 ELMBANK CRES</p>]]></description>      <Point>        <coordinates> -75.74997732207535,45.34883506560314,0</coordinates>      </Point><Style><IconStyle><Icon><href>http://www.iconeasy.com/icon/thumbnails/Kids/Freestyle%20Icons/Tree%20Icon.jpg</href></Icon></IconStyle></Style>    </Placemark>    <Placemark id="ID_031939"><name>Fir</name><description><![CDATA[<p>1681 DES SAPINS GDN</p>]]></description>      <Point>        <coordinates> -75.53742962071894,45.45759816919387,0</coordinates>      </Point><Style><IconStyle><Icon><href>http://www.iconeasy.com/icon/thumbnails/Kids/Freestyle%20Icons/Tree%20Icon.jpg</href></Icon></IconStyle></Style>    </Placemark>    <Placemark id="ID_034142"><name>Fir</name><description><![CDATA[<p>178 CLEARVIEW AVE</p>]]></description>      <Point>        <coordinates> -75.75024186568572,45.40011406416858,0</coordinates>      </Point><Style><IconStyle><Icon><href>http://www.iconeasy.com/icon/thumbnails/Kids/Freestyle%20Icons/Tree%20Icon.jpg</href></Icon></IconStyle></Style>    </Placemark>    <Placemark id="ID_034778"><name>Fir</name><description><![CDATA[<p>171 LANARK AVE</p>]]></description>      <Point>        <coordinates> -75.74998755744696,45.3996640328233,0</coordinates>      </Point><Style><IconStyle><Icon><href>http://www.iconeasy.com/icon/thumbnails/Kids/Freestyle%20Icons/Tree%20Icon.jpg</href></Icon></IconStyle></Style>    </Placemark></Document></kml>